__init__.py
compare_hkl.py
corrected_to_adsc.py
main.py
plot_imgs_w_spots.py
plot_integrate.py
plot_smv_side_by_side.py
plot_spot.py
plot_spot_radial.py
plot_tiff_side_by_side.py
plot_xds_ascii.py
prepare_shelx.py
run_xds.py
zenodo_to_redp.py
archive/plot_rounding_effect.py
lib/__init__.py
lib/adscimage.py
lib/central_cross_correction_factor.py
lib/find_cred_project.py
lib/mib.py
pets/__init__.py
pets/calibrate_angles.py
pets/camel.py
pets/center_cross_correction.py
pets/create_bs.py
pets/mark_dead_pixels.py
pets/run_shelx.py
xds/calibrate.py
crysm-1.0.1.dist-info/METADATA
crysm-1.0.1.dist-info/WHEEL
crysm-1.0.1.dist-info/entry_points.txt
crysm-1.0.1.dist-info/top_level.txt
crysm-1.0.1.dist-info/RECORD
