Metadata-Version: 2.4
Name: crysm
Version: 1.0.1
Summary: Continuous rotation electron diffraction (cRED) data analysis helper cli
Classifier: Development Status :: 3 - Alpha
Classifier: Intended Audience :: Science/Research
Classifier: Topic :: Scientific/Engineering :: Physics
Classifier: Programming Language :: Python :: 3
Classifier: Operating System :: OS Independent
Requires-Python: >=3.10
Requires-Dist: click==8.1.8
Requires-Dist: imagecodecs>=2025.3.30
Requires-Dist: numpy>1.24.4
Requires-Dist: matplotlib>=3.7.5
Requires-Dist: pydantic>=2.11.3
Requires-Dist: rich>=13.7.1
Requires-Dist: tifffile>=2025.5.10
Requires-Dist: typer>=0.15.2
Requires-Dist: pyyaml>=6.0.0
Provides-Extra: dev
Requires-Dist: ipympl>=0.9.3; extra == "dev"
Requires-Dist: jupyter>=1.1.1; extra == "dev"
Requires-Dist: pyxem>=0.20.0; extra == "dev"
Provides-Extra: docs
Requires-Dist: mkdocs; extra == "docs"
Requires-Dist: mkdocs-typer2; extra == "docs"
Requires-Dist: pymdown-extensions; extra == "docs"
Requires-Dist: mkdocs-material; extra == "docs"
